// converted by version 1.3
// on Fri Mar 11 15:42:16 CET 2016

.package henrik {
	.aid 0x1:0x2:0x3:0x4:0x5:0x6:0x7:0x8:0x9:0x0;
	.version 1.0;

	.imports {
		0xA0:0x0:0x0:0x0:0x62:0x1:0x1 1.3;		//javacard/framework
		0xA0:0x0:0x0:0x0:0x62:0x2:0x9 1.0;		//javacardx/apdu
		0xA0:0x0:0x0:0x0:0x62:0x1:0x2 1.3;		//javacard/security
		0xA0:0x0:0x0:0x0:0x62:0x2:0x1 1.3;		//javacardx/crypto
		0xA0:0x0:0x0:0x0:0x62:0x0:0x1 1.0;		//java/lang
	}

	.applet {
		0x1:0x2:0x3:0x4:0x5:0x6:0x7:0x8:0x9:0x0:0x7 cardTest;
	}

	.constantPool {
		// 0
		instanceFieldRef byte[] cardTest/test;
		// 1
		instanceFieldRef byte[] cardTest/output;
		// 2
		instanceFieldRef byte[] cardTest/buff2;
		// 3
		instanceFieldRef short cardTest/keysize;
		// 4
		instanceFieldRef byte cardTest/MAX_LENGTH;
		// 5
		instanceFieldRef byte cardTest/MAX_ATTEMPTS;
		// 6
		instanceFieldRef byte cardTest/CLA;
		// 7
		instanceFieldRef byte cardTest/SEND_TEST_SIGNATURE;
		// 8
		instanceFieldRef byte cardTest/SEND_PUB_MOD;
		// 9
		instanceFieldRef byte cardTest/SEND_PUB_EXP;
		// 10
		instanceFieldRef byte cardTest/SEND_PRV_EXP;
		// 11
		instanceFieldRef byte cardTest/SEND_KEY_LENGTH;
		// 12
		instanceFieldRef byte cardTest/SIGN_INPUT_DATA;
		// 13
		instanceFieldRef byte cardTest/SEND_AUTHENTICATED_PUB_EXP;
		// 14
		instanceFieldRef short cardTest/policy13Offset;
		// 15
		instanceFieldRef byte cardTest/PIN_TRY_LIMIT;
		// 16
		instanceFieldRef byte cardTest/PIN_SIZE;
		// 17
		instanceFieldRef byte cardTest/INCOMING_PIN_OFFSET;
		// 18
		instanceFieldRef byte[] cardTest/h0Buffer;
		// 19
		instanceFieldRef byte cardTest/pinIsPresentFlag;
		// 20
		instanceFieldRef 0.9 cardTest/pincode;
		// 21
		instanceFieldRef 2.16 cardTest/keys;
		// 22
		instanceFieldRef 2.15 cardTest/sig;
		// 23
		instanceFieldRef 2.9 cardTest/k;
		// 24
		instanceFieldRef 2.8 cardTest/k2;
		// 25
		instanceFieldRef 3.1 cardTest/cipherRSA;
		// 26
		instanceFieldRef 3.1 cardTest/cipherAES;
		// 27
		instanceFieldRef 2.20 cardTest/aesKey;
		// 28
		instanceFieldRef 2.14 cardTest/randomData;
		// 29
		instanceFieldRef byte[] cardTest/rnd;
		// 30
		instanceFieldRef short cardTest/size;
		// 31
		instanceFieldRef 0.9 cardTest/pin;
		// 32
		instanceFieldRef byte[] cardTest/cryptoBuffer;
		// 33
		virtualMethodRef 2.16.1()V;		// genKeyPair()V
		// 34
		virtualMethodRef 2.16.3()Ljavacard/security/PublicKey;;		// getPublic()Ljavacard/security/PublicKey;
			.descriptor	Ljavacard/security/PublicKey;	2.3;

		// 35
		classRef 2.9;		// javacard/security/RSAPublicKey
		// 36
		classRef 2.12;		// javacard/security/CryptoException
		// 37
		virtualMethodRef 2.16.2()Ljavacard/security/PrivateKey;;		// getPrivate()Ljavacard/security/PrivateKey;
			.descriptor	Ljavacard/security/PrivateKey;	2.2;

		// 38
		classRef 2.8;		// javacard/security/RSAPrivateKey
		// 39
		classRef 0.9;		// javacard/framework/OwnerPIN
		// 40
		virtualMethodRef 2.15.3(Ljavacard/security/Key;B)V;		// init(Ljavacard/security/Key;B)V
			.descriptor	Ljavacard/security/Key;	2.0;

		// 41
		staticMethodRef 3.1.0(BZ)Ljavacardx/crypto/Cipher;;		// javacardx/crypto/Cipher.getInstance(BZ)Ljavacardx/crypto/Cipher;
			.descriptor	Ljavacardx/crypto/Cipher;	3.1;

		// 42
		staticMethodRef 0.9.0(BB)V;		// javacard/framework/OwnerPIN.<init>(BB)V
		// 43
		staticMethodRef 0.3.0()V;		// javacard/framework/Applet.<init>()V
		// 44
		staticMethodRef 2.13.0(BSZ)Ljavacard/security/Key;;		// javacard/security/KeyBuilder.buildKey(BSZ)Ljavacard/security/Key;
			.descriptor	Ljavacard/security/Key;	2.0;

		// 45
		classRef 2.20;		// javacard/security/AESKey
		// 46
		virtualMethodRef 0.9.8([BSB)V;		// update([BSB)V
		// 47
		staticMethodRef 2.14.0(B)Ljavacard/security/RandomData;;		// javacard/security/RandomData.getInstance(B)Ljavacard/security/RandomData;
			.descriptor	Ljavacard/security/RandomData;	2.14;

		// 48
		classRef 2.16;		// javacard/security/KeyPair
		// 49
		staticMethodRef 0.8.13(SB)[B;		// javacard/framework/JCSystem.makeTransientByteArray(SB)[B
		// 50
		staticMethodRef 2.16.0(BS)V;		// javacard/security/KeyPair.<init>(BS)V
		// 51
		virtualMethodRef 2.14.1([BSS)V;		// generateData([BSS)V
		// 52
		virtualMethodRef 2.12.1()S;		// getReason()S
		// 53
		staticMethodRef 0.7.1(S)V;		// javacard/framework/ISOException.throwIt(S)V
		// 54
		classRef cardTest;
		// 55
		staticMethodRef cardTest/<init>()V;
		// 56
		virtualMethodRef 0.3.1()V;		// register()V
		// 57
		virtualMethodRef 0.3.3()Z;		// selectingApplet()Z
		// 58
		virtualMethodRef 0.10.1()[B;		// getBuffer()[B
		// 59
		virtualMethodRef 2.15.5([BSS[BS)S;		// sign([BSS[BS)S
		// 60
		classRef 4.10;		// java/lang/SecurityException
		// 61
		staticMethodRef 2.15.0(BZ)Ljavacard/security/Signature;;		// javacard/security/Signature.getInstance(BZ)Ljavacard/security/Signature;
			.descriptor	Ljavacard/security/Signature;	2.15;

		// 62
		virtualMethodRef 0.9.1([BSB)Z;		// check([BSB)Z
		// 63
		virtualMethodRef 0.9.5()V;		// reset()V
		// 64
		staticMethodRef cardTest/shortToByteArray(S)V;
		// 65
		staticMethodRef 0.16.1([BS[BSS)S;		// javacard/framework/Util.arrayCopy([BS[BSS)S
		// 66
		virtualMethodRef 0.9.4()Z;		// isValidated()Z
		// 67
		virtualMethodRef 0.9.2()B;		// getTriesRemaining()B
		// 68
		virtualMethodRef 3.1.3(Ljavacard/security/Key;B)V;		// init(Ljavacard/security/Key;B)V
			.descriptor	Ljavacard/security/Key;	2.0;

		// 69
		virtualMethodRef 0.10.6()S;		// setIncomingAndReceive()S
		// 70
		virtualMethodRef 0.10.15()S;		// getIncomingLength()S
		// 71
		classRef 4.2;		// java/lang/Exception
		// 72
		virtualMethodRef 3.1.1([BSS[BS)S;		// doFinal([BSS[BS)S
		// 73
		staticMethodRef cardTest/send(Ljavacard/framework/APDU;)V;
			.descriptor	Ljavacard/framework/APDU;	0.10;

		// 74
		staticMethodRef 0.16.2([BS[BSS)S;		// javacard/framework/Util.arrayCopyNonAtomic([BS[BSS)S
		// 75
		virtualMethodRef 0.10.3(S)S;		// receiveBytes(S)S
		// 76
		virtualMethodRef 0.10.7()S;		// setOutgoing()S
		// 77
		virtualMethodRef 0.10.9(S)V;		// setOutgoingLength(S)V
		// 78
		virtualMethodRef 0.10.5([BSS)V;		// sendBytesLong([BSS)V
		// 79
		virtualMethodRef 0.10.8(SS)V;		// setOutgoingAndSend(SS)V
	}

	.class public cardTest 0 extends 0.3 {		// extends javacard/framework/Applet

		.fields {
			private 2.16 keys 0;		// Ljavacard/security/KeyPair;
			private 2.15 sig 1;		// Ljavacard/security/Signature;
			private 2.9 k 2;		// Ljavacard/security/RSAPublicKey;
			private 2.8 k2 3;		// Ljavacard/security/RSAPrivateKey;
			 byte[] test 4;		// [B
			 byte[] output 5;		// [B
			 byte[] buff2 6;		// [B
			 byte[] bigArray 7;		// [B
			private 0.9 pin 8;		// Ljavacard/framework/OwnerPIN;
			 3.1 cipherRSA 9;		// Ljavacardx/crypto/Cipher;
			 3.1 cipherAES 10;		// Ljavacardx/crypto/Cipher;
			 byte[] cryptoBuffer 11;		// [B
			 2.20 aesKey 12;		// Ljavacard/security/AESKey;
			 2.14 randomData 13;		// Ljavacard/security/RandomData;
			 byte[] rnd 14;		// [B
			 0.9 pincode 15;		// Ljavacard/framework/OwnerPIN;
			 byte[] h0Buffer 16;		// [B
			 short size 17;		// S
			 short len 18;		// S
			final short keysize 19;		// S
			private final byte MAX_LENGTH 20;		// B
			private final byte MAX_ATTEMPTS 21;		// B
			private final byte CLA 22;		// B
			private final byte SEND_TEST_SIGNATURE 23;		// B
			private final byte SEND_PUB_MOD 24;		// B
			private final byte SEND_PUB_EXP 25;		// B
			private final byte SEND_PRV_EXP 26;		// B
			private final byte SEND_KEY_LENGTH 27;		// B
			private final byte SIGN_INPUT_DATA 28;		// B
			private final byte SEND_AUTHENTICATED_PUB_EXP 29;		// B
			 short policy13Offset 30;		// S
			 byte pinIsPresentFlag 31;		// B
			final byte PIN_TRY_LIMIT 32;		// B
			final byte PIN_SIZE 33;		// B
			final byte INCOMING_PIN_OFFSET 34;		// B
		}

		.publicMethodTable 7 {
			equals(Ljava/lang/Object;)Z;
			register()V;
			register([BSB)V;
			selectingApplet()Z;
			deselect()V;
			getShareableInterfaceObject(Ljavacard/framework/AID;B)Ljavacard/framework/Shareable;;
			select()Z;
			process(Ljavacard/framework/APDU;)V;
		}

		.packageMethodTable 0 {
		}

		.implementedInterfaceInfoTable { 
			.interface 1.0 { 		// javacardx/apdu/ExtendedLength
			}

		}

		.method private <init>()V {
			.stack 5;
			.locals 1;

				L0:	aload_0;
					invokespecial 43;		// javacard/framework/Applet.<init>()V
					aload_0;
					bspush 6;
					newarray 11;
					dup;
					sconst_0;
					sconst_1;
					bastore;
					dup;
					sconst_1;
					sconst_2;
					bastore;
					dup;
					sconst_2;
					sconst_4;
					bastore;
					dup;
					sconst_3;
					sconst_5;
					bastore;
					dup;
					sconst_4;
					bspush 6;
					bastore;
					dup;
					sconst_5;
					bspush 7;
					bastore;
					putfield_a 0;		// reference henrik/cardTest.test
					aload_0;
					sspush 32767;
					newarray 11;
					putfield_a 1;		// reference henrik/cardTest.output
					aload_0;
					sconst_2;
					newarray 11;
					putfield_a 2;		// reference henrik/cardTest.buff2
					aload_0;
					bspush 64;
					putfield_s 3;		// short henrik/cardTest.keysize
					aload_0;
					sconst_4;
					putfield_b 4;		// byte henrik/cardTest.MAX_LENGTH
					aload_0;
					sconst_5;
					putfield_b 5;		// byte henrik/cardTest.MAX_ATTEMPTS
					aload_0;
					bspush -128;
					putfield_b 6;		// byte henrik/cardTest.CLA
					aload_0;
					sconst_0;
					putfield_b 7;		// byte henrik/cardTest.SEND_TEST_SIGNATURE
					aload_0;
					sconst_1;
					putfield_b 8;		// byte henrik/cardTest.SEND_PUB_MOD
					aload_0;
					sconst_2;
					putfield_b 9;		// byte henrik/cardTest.SEND_PUB_EXP
					aload_0;
					sconst_3;
					putfield_b 10;		// byte henrik/cardTest.SEND_PRV_EXP
					aload_0;
					sconst_4;
					putfield_b 11;		// byte henrik/cardTest.SEND_KEY_LENGTH
					aload_0;
					sconst_5;
					putfield_b 12;		// byte henrik/cardTest.SIGN_INPUT_DATA
					aload_0;
					bspush 6;
					putfield_b 13;		// byte henrik/cardTest.SEND_AUTHENTICATED_PUB_EXP
					aload_0;
					bspush 6;
					putfield_s 14;		// short henrik/cardTest.policy13Offset
					aload_0;
					sconst_3;
					putfield_b 15;		// byte henrik/cardTest.PIN_TRY_LIMIT
					aload_0;
					sconst_4;
					putfield_b 16;		// byte henrik/cardTest.PIN_SIZE
					aload_0;
					sconst_0;
					putfield_b 17;		// byte henrik/cardTest.INCOMING_PIN_OFFSET
					aload_0;
					sspush 32767;
					newarray 11;
					putfield_a 18;		// reference henrik/cardTest.h0Buffer
				L1:	aload_0;
					sconst_0;
					putfield_b 19;		// byte henrik/cardTest.pinIsPresentFlag
					aload_0;
					new 39;		// javacard/framework/OwnerPIN
					dup;
					sconst_3;
					sconst_4;
					invokespecial 42;		// javacard/framework/OwnerPIN.<init>(BB)V
					putfield_a 20;		// reference henrik/cardTest.pincode
					sconst_4;
					newarray 11;
					dup;
					sconst_0;
					sconst_1;
					bastore;
					dup;
					sconst_1;
					sconst_3;
					bastore;
					dup;
					sconst_2;
					sconst_3;
					bastore;
					dup;
					sconst_3;
					bspush 7;
					bastore;
					astore_1;
					getfield_a_this 20;		// reference henrik/cardTest.pincode
					aload_1;
					sconst_0;
					sconst_4;
					invokevirtual 46;		// update([BSB)V
					aload_0;
					new 48;		// javacard/security/KeyPair
					dup;
					sconst_1;
					sspush 512;
					invokespecial 50;		// javacard/security/KeyPair.<init>(BS)V
					putfield_a 21;		// reference henrik/cardTest.keys
					aload_0;
					bspush 10;
					sconst_0;
					invokestatic 61;		// javacard/security/Signature.getInstance(BZ)Ljavacard/security/Signature;
					putfield_a 22;		// reference henrik/cardTest.sig
					getfield_a_this 21;		// reference henrik/cardTest.keys
					invokevirtual 33;		// genKeyPair()V
					aload_0;
					getfield_a_this 21;		// reference henrik/cardTest.keys
					invokevirtual 34;		// getPublic()Ljavacard/security/PublicKey;
					checkcast 0 35;		// T_CLASSORINTERFACE javacard/security/RSAPublicKey
					putfield_a 23;		// reference henrik/cardTest.k
					aload_0;
					getfield_a_this 21;		// reference henrik/cardTest.keys
					invokevirtual 37;		// getPrivate()Ljavacard/security/PrivateKey;
					checkcast 0 38;		// T_CLASSORINTERFACE javacard/security/RSAPrivateKey
					putfield_a 24;		// reference henrik/cardTest.k2
					getfield_a_this 22;		// reference henrik/cardTest.sig
					getfield_a_this 24;		// reference henrik/cardTest.k2
					sconst_1;
					invokevirtual 40;		// init(Ljavacard/security/Key;B)V
					aload_0;
					bspush 10;
					sconst_0;
					invokestatic 41;		// javacardx/crypto/Cipher.getInstance(BZ)Ljavacardx/crypto/Cipher;
					putfield_a 25;		// reference henrik/cardTest.cipherRSA
					aload_0;
					bspush 13;
					sconst_0;
					invokestatic 41;		// javacardx/crypto/Cipher.getInstance(BZ)Ljavacardx/crypto/Cipher;
					putfield_a 26;		// reference henrik/cardTest.cipherAES
					aload_0;
					bspush 15;
					sspush 128;
					sconst_0;
					invokestatic 44;		// javacard/security/KeyBuilder.buildKey(BSZ)Ljavacard/security/Key;
					checkcast 0 45;		// T_CLASSORINTERFACE javacard/security/AESKey
					putfield_a 27;		// reference henrik/cardTest.aesKey
					aload_0;
					sconst_1;
					invokestatic 47;		// javacard/security/RandomData.getInstance(B)Ljavacard/security/RandomData;
					putfield_a 28;		// reference henrik/cardTest.randomData
					aload_0;
					bspush 16;
					sconst_1;
					invokestatic 49;		// javacard/framework/JCSystem.makeTransientByteArray(SB)[B
					putfield_a 29;		// reference henrik/cardTest.rnd
					getfield_a_this 28;		// reference henrik/cardTest.randomData
					getfield_a_this 29;		// reference henrik/cardTest.rnd
					sconst_0;
					getfield_a_this 29;		// reference henrik/cardTest.rnd
					arraylength;
					invokevirtual 51;		// generateData([BSS)V
					getfield_a_this 27;		// reference henrik/cardTest.aesKey
					getfield_a_this 29;		// reference henrik/cardTest.rnd
					sconst_0;
					invokeinterface 3 45 4;		// javacard/security/AESKey
				L2:	goto L6;
				L3:	astore_1;
					aload_1;
					invokevirtual 52;		// getReason()S
					invokestatic 53;		// javacard/framework/ISOException.throwIt(S)V
					goto L6;
				L4:	astore_1;
					sspush 28432;
					invokestatic 53;		// javacard/framework/ISOException.throwIt(S)V
					goto L6;
				L5:	astore_1;
					sspush 28448;
					invokestatic 53;		// javacard/framework/ISOException.throwIt(S)V
				L6:	return;
			.exceptionTable {
				// start_block end_block handler_block catch_type_index
				L1 L2 L3 36;
				L1 L2 L4 60;
				L1 L2 L5 71;
			}
		}

		.method public static install([BSB)V 0 {
			.stack 2;
			.locals 0;

				L0:	new 54;		// henrik/cardTest
					dup;
					invokespecial 55;		// henrik/cardTest.<init>()V
					invokevirtual 56;		// register()V
					return;
		}

		.method public process(Ljavacard/framework/APDU;)V 7 {
			.stack 7;
			.locals 12;

			.descriptor	Ljavacard/framework/APDU;	0.10;

				L0:	aload_0;
					invokevirtual 57;		// selectingApplet()Z
					ifeq L2;
				L1:	return;
				L2:	aload_1;
					invokevirtual 58;		// getBuffer()[B
					astore_2;
					bspush 7;
					sstore_3;
					aload_2;
					sconst_1;
					baload;
					stableswitch L48 0 9 L3 L4 L5 L6 L14 L15 L25 L33 L34 L38;
				L3:	aload_0;
					getfield_a_this 22;		// reference henrik/cardTest.sig
					getfield_a_this 0;		// reference henrik/cardTest.test
					sconst_0;
					getfield_a_this 0;		// reference henrik/cardTest.test
					arraylength;
					getfield_a_this 1;		// reference henrik/cardTest.output
					sconst_0;
					invokevirtual 59;		// sign([BSS[BS)S
					putfield_s 30;		// short henrik/cardTest.size
					goto_w L49;
				L4:	aload_0;
					getfield_a_this 23;		// reference henrik/cardTest.k
					getfield_a_this 1;		// reference henrik/cardTest.output
					sconst_0;
					invokeinterface 3 35 5;		// javacard/security/RSAPublicKey
					putfield_s 30;		// short henrik/cardTest.size
					goto_w L49;
				L5:	aload_0;
					getfield_a_this 23;		// reference henrik/cardTest.k
					getfield_a_this 1;		// reference henrik/cardTest.output
					sconst_0;
					invokeinterface 3 35 4;		// javacard/security/RSAPublicKey
					putfield_s 30;		// short henrik/cardTest.size
					goto_w L49;
				L6:	aload_2;
					sconst_2;
					baload;
					sconst_1;
					if_scmpne L12;
				L7:	aload_2;
					sconst_4;
					baload;
					ifeq L11;
				L8:	getfield_a_this 31;		// reference henrik/cardTest.pin
					aload_2;
					sconst_5;
					aload_2;
					sconst_4;
					baload;
					invokevirtual 62;		// check([BSB)Z
					ifeq L10;
				L9:	aload_0;
					getfield_a_this 24;		// reference henrik/cardTest.k2
					getfield_a_this 1;		// reference henrik/cardTest.output
					sconst_0;
					invokeinterface 3 38 4;		// javacard/security/RSAPrivateKey
					putfield_s 30;		// short henrik/cardTest.size
					getfield_a_this 31;		// reference henrik/cardTest.pin
					invokevirtual 63;		// reset()V
					goto L13;
				L10:	sspush 27264;
					invokestatic 53;		// javacard/framework/ISOException.throwIt(S)V
					goto L13;
				L11:	sspush 27013;
					invokestatic 53;		// javacard/framework/ISOException.throwIt(S)V
					goto L13;
				L12:	sspush 27270;
					invokestatic 53;		// javacard/framework/ISOException.throwIt(S)V
				L13:	aload_0;
					getfield_a_this 24;		// reference henrik/cardTest.k2
					getfield_a_this 1;		// reference henrik/cardTest.output
					sconst_0;
					invokeinterface 3 38 4;		// javacard/security/RSAPrivateKey
					putfield_s 30;		// short henrik/cardTest.size
					goto_w L49;
				L14:	aload_0;
					bspush 64;
					invokespecial 64;		// henrik/cardTest.shortToByteArray(S)V
					aload_0;
					sconst_2;
					putfield_s 30;		// short henrik/cardTest.size
					aload_2;
					sconst_0;
					getfield_a_this 1;		// reference henrik/cardTest.output
					sconst_0;
					getfield_s_this 30;		// short henrik/cardTest.size
					invokestatic 65;		// javacard/framework/Util.arrayCopy([BS[BSS)S
					pop;
					goto_w L49;
				L15:	aload_2;
					sconst_2;
					baload;
					sstore 4;
					sload 4;
					sconst_1;
					if_scmpne L20;
				L16:	getfield_a_this 1;		// reference henrik/cardTest.output
					sconst_0;
					sconst_5;
					bastore;
					getfield_a_this 20;		// reference henrik/cardTest.pincode
					invokevirtual 66;		// isValidated()Z
					ifeq L18;
				L17:	getfield_a_this 1;		// reference henrik/cardTest.output
					sconst_1;
					sconst_1;
					bastore;
					goto L19;
				L18:	getfield_a_this 1;		// reference henrik/cardTest.output
					sconst_1;
					sconst_0;
					bastore;
				L19:	getfield_a_this 1;		// reference henrik/cardTest.output
					sconst_2;
					getfield_a_this 20;		// reference henrik/cardTest.pincode
					invokevirtual 67;		// getTriesRemaining()B
					bastore;
					getfield_a_this 1;		// reference henrik/cardTest.output
					sconst_3;
					sconst_5;
					bastore;
					getfield_a_this 1;		// reference henrik/cardTest.output
					sconst_4;
					sconst_5;
					bastore;
					getfield_a_this 1;		// reference henrik/cardTest.output
					sconst_5;
					sconst_5;
					bastore;
					aload_0;
					bspush 6;
					putfield_s 30;		// short henrik/cardTest.size
					goto_w L49;
				L20:	sload 4;
					sconst_2;
					if_scmpne L22;
				L21:	getfield_a_this 1;		// reference henrik/cardTest.output
					sconst_0;
					sconst_5;
					bastore;
					getfield_a_this 1;		// reference henrik/cardTest.output
					sconst_1;
					sconst_2;
					bastore;
					getfield_a_this 1;		// reference henrik/cardTest.output
					sconst_2;
					sconst_2;
					bastore;
					getfield_a_this 1;		// reference henrik/cardTest.output
					sconst_3;
					sconst_3;
					bastore;
					getfield_a_this 1;		// reference henrik/cardTest.output
					sconst_4;
					sconst_3;
					bastore;
					aload_0;
					bspush 7;
					putfield_s 30;		// short henrik/cardTest.size
					goto_w L49;
				L22:	sload 4;
					sconst_3;
					if_scmpne_w L49;
				L23:	getfield_a_this 20;		// reference henrik/cardTest.pincode
					invokevirtual 66;		// isValidated()Z
					ifne_w L49;
				L24:	sspush 27010;
					invokestatic 53;		// javacard/framework/ISOException.throwIt(S)V
					goto_w L49;
				L25:	aload_2;
					sconst_2;
					baload;
					sstore 5;
					sload 5;
					sconst_1;
					if_scmpne L27;
				L26:	getfield_a_this 25;		// reference henrik/cardTest.cipherRSA
					getfield_a_this 23;		// reference henrik/cardTest.k
					sconst_2;
					invokevirtual 68;		// init(Ljavacard/security/Key;B)V
					goto L29;
				L27:	sload 5;
					sconst_2;
					if_scmpne L29;
				L28:	getfield_a_this 25;		// reference henrik/cardTest.cipherRSA
					getfield_a_this 24;		// reference henrik/cardTest.k2
					sconst_1;
					invokevirtual 68;		// init(Ljavacard/security/Key;B)V
				L29:	aload_1;
					invokevirtual 69;		// setIncomingAndReceive()S
					sstore 6;
					aload_0;
					aload_1;
					invokevirtual 70;		// getIncomingLength()S
					putfield_s 30;		// short henrik/cardTest.size
					sconst_0;
					sstore 7;
					goto L31;
				L30:	aload_2;
					sload_3;
					getfield_a_this 32;		// reference henrik/cardTest.cryptoBuffer
					sload 7;
					sload 6;
					invokestatic 74;		// javacard/framework/Util.arrayCopyNonAtomic([BS[BSS)S
					pop;
					sload 7;
					sload 6;
					sadd;
					sstore 7;
					aload_1;
					sload_3;
					invokevirtual 75;		// receiveBytes(S)S
					sstore 6;
				L31:	sload 6;
					ifgt L30;
				L32:	aload_0;
					getfield_a_this 25;		// reference henrik/cardTest.cipherRSA
					getfield_a_this 32;		// reference henrik/cardTest.cryptoBuffer
					sconst_0;
					getfield_s_this 30;		// short henrik/cardTest.size
					getfield_a_this 1;		// reference henrik/cardTest.output
					sconst_0;
					invokevirtual 72;		// doFinal([BSS[BS)S
					putfield_s 30;		// short henrik/cardTest.size
					goto_w L49;
				L33:	goto_w L49;
				L34:	aload_1;
					invokevirtual 69;		// setIncomingAndReceive()S
					sstore 8;
					aload_0;
					aload_1;
					invokevirtual 70;		// getIncomingLength()S
					putfield_s 30;		// short henrik/cardTest.size
					sconst_0;
					sstore 9;
					goto L36;
				L35:	aload_2;
					sload_3;
					getfield_a_this 1;		// reference henrik/cardTest.output
					sload 9;
					sload 8;
					invokestatic 74;		// javacard/framework/Util.arrayCopyNonAtomic([BS[BSS)S
					pop;
					sload 9;
					sload 8;
					sadd;
					sstore 9;
					aload_1;
					sload_3;
					invokevirtual 75;		// receiveBytes(S)S
					sstore 8;
				L36:	sload 8;
					ifgt L35;
				L37:	goto_w L49;
				L38:	aload_2;
					sconst_2;
					baload;
					sstore 10;
					sload 10;
					sconst_1;
					if_scmpne L40;
				L39:	getfield_a_this 26;		// reference henrik/cardTest.cipherAES
					getfield_a_this 27;		// reference henrik/cardTest.aesKey
					sconst_2;
					invokevirtual 68;		// init(Ljavacard/security/Key;B)V
					goto L42;
				L40:	sload 10;
					sconst_2;
					if_scmpne L42;
				L41:	getfield_a_this 26;		// reference henrik/cardTest.cipherAES
					getfield_a_this 27;		// reference henrik/cardTest.aesKey
					sconst_1;
					invokevirtual 68;		// init(Ljavacard/security/Key;B)V
				L42:	aload_1;
					invokevirtual 69;		// setIncomingAndReceive()S
					sstore 11;
					aload_0;
					aload_1;
					invokevirtual 70;		// getIncomingLength()S
					putfield_s 30;		// short henrik/cardTest.size
					sconst_0;
					sstore 12;
					goto L44;
				L43:	aload_2;
					sload_3;
					getfield_a_this 32;		// reference henrik/cardTest.cryptoBuffer
					sload 12;
					sload 11;
					invokestatic 74;		// javacard/framework/Util.arrayCopyNonAtomic([BS[BSS)S
					pop;
					sload 12;
					sload 11;
					sadd;
					sstore 12;
					aload_1;
					sload_3;
					invokevirtual 75;		// receiveBytes(S)S
					sstore 11;
				L44:	sload 11;
					ifgt L43;
				L45:	aload_0;
					getfield_a_this 26;		// reference henrik/cardTest.cipherAES
					getfield_a_this 32;		// reference henrik/cardTest.cryptoBuffer
					sconst_0;
					getfield_s_this 30;		// short henrik/cardTest.size
					getfield_a_this 1;		// reference henrik/cardTest.output
					sconst_0;
					invokevirtual 72;		// doFinal([BSS[BS)S
					putfield_s 30;		// short henrik/cardTest.size
				L46:	goto L49;
				L47:	astore 13;
					aload_0;
					sconst_2;
					putfield_s 30;		// short henrik/cardTest.size
					getfield_a_this 1;		// reference henrik/cardTest.output
					sconst_0;
					aload 13;
					invokevirtual 52;		// getReason()S
					s2b;
					bastore;
					getfield_a_this 1;		// reference henrik/cardTest.output
					sconst_1;
					sconst_2;
					bastore;
					goto L49;
				L48:	sspush 27904;
					invokestatic 53;		// javacard/framework/ISOException.throwIt(S)V
				L49:	aload_0;
					aload_1;
					invokespecial 73;		// henrik/cardTest.send(Ljavacard/framework/APDU;)V
					return;
			.exceptionTable {
				// start_block end_block handler_block catch_type_index
				L45 L46 L47 36;
			}
		}

		.method private shortToByteArray(S)V {
			.stack 4;
			.locals 0;

				L0:	getfield_a_this 2;		// reference henrik/cardTest.buff2
					sconst_0;
					sload_1;
					sspush -256;
					sand;
					bspush 8;
					sshr;
					s2b;
					bastore;
					getfield_a_this 2;		// reference henrik/cardTest.buff2
					sconst_1;
					sload_1;
					sspush 255;
					sand;
					s2b;
					bastore;
					return;
		}

		.method private send(Ljavacard/framework/APDU;)V {
			.stack 4;
			.locals 0;

			.descriptor	Ljavacard/framework/APDU;	0.10;

				L0:	aload_1;
					invokevirtual 76;		// setOutgoing()S
					pop;
					aload_1;
					getfield_s_this 30;		// short henrik/cardTest.size
					invokevirtual 77;		// setOutgoingLength(S)V
					aload_1;
					getfield_a_this 1;		// reference henrik/cardTest.output
					sconst_0;
					getfield_s_this 30;		// short henrik/cardTest.size
					invokevirtual 78;		// sendBytesLong([BSS)V
					return;
		}

		.method private sendBuff(Ljavacard/framework/APDU;)V {
			.stack 3;
			.locals 0;

			.descriptor	Ljavacard/framework/APDU;	0.10;

				L0:	aload_1;
					sconst_0;
					getfield_s_this 30;		// short henrik/cardTest.size
					invokevirtual 79;		// setOutgoingAndSend(SS)V
					return;
		}

	}

}
